LICENSE.txt
MANIFEST.in
README.md
setup.py
levit_report/__init__.py
levit_report/admin.py
levit_report/models.py
levit_report/tests.py
levit_report/urls.py
levit_report/utils.py
levit_report/views.py
levit_report.egg-info/PKG-INFO
levit_report.egg-info/SOURCES.txt
levit_report.egg-info/dependency_links.txt
levit_report.egg-info/requires.txt
levit_report.egg-info/top_level.txt
levit_report/migrations/0001_initial.py
levit_report/migrations/0002_auto_20170114_0758.py
levit_report/migrations/0003_auto_20170308_1431.py
levit_report/migrations/0004_document_is_default_for_ct.py
levit_report/migrations/__init__.py