Metadata-Version: 2.1
Name: levit-report
Version: 3.0
Summary: Bring the power of relatorio to Django
Home-page: http://levit.be
Author: LevIT scs
Author-email: foss@levit.be
License: MIT License
Classifier: Environment :: Web Environment
Classifier: Framework :: Django
Classifier: Framework :: Django :: 4.2
Classifier: Intended Audience :: Developers
Classifier: License :: OSI Approved :: MIT License
Classifier: Operating System :: OS Independent
Classifier: Programming Language :: Python
Classifier: Programming Language :: Python :: 3
Classifier: Programming Language :: Python :: 3.11
Classifier: Topic :: Internet :: WWW/HTTP
Classifier: Topic :: Internet :: WWW/HTTP :: Dynamic Content
License-File: LICENSE.txt
Requires-Dist: Django>=4.2
Requires-Dist: relatorio>=0.10.1
